<annotation>
	<folder>Train</folder>
	<filename>20200816_183318.jpg</filename>
	<path>D:\PROJECTS\prototype\images\Train\20200816_183318.jpg</path>
	<source>
		<database>Unknown</database>
	</source>
	<size>
		<width>640</width>
		<height>640</height>
		<depth>3</depth>
	</size>
	<segmented>0</segmented>
	<object>
		<name>eggs</name>
		<pose>Unspecified</pose>
		<truncated>0</truncated>
		<difficult>0</difficult>
		<bndbox>
			<xmin>161</xmin>
			<ymin>215</ymin>
			<xmax>266</xmax>
			<ymax>294</ymax>
		</bndbox>
	</object>
	<object>
		<name>eggs</name>
		<pose>Unspecified</pose>
		<truncated>0</truncated>
		<difficult>0</difficult>
		<bndbox>
			<xmin>323</xmin>
			<ymin>231</ymin>
			<xmax>446</xmax>
			<ymax>313</ymax>
		</bndbox>
	</object>
</annotation>
