<annotation>
	<folder>Train</folder>
	<filename>20200816_183135.jpg</filename>
	<path>D:\PROJECTS\prototype\images\Train\20200816_183135.jpg</path>
	<source>
		<database>Unknown</database>
	</source>
	<size>
		<width>640</width>
		<height>640</height>
		<depth>3</depth>
	</size>
	<segmented>0</segmented>
	<object>
		<name>eggs</name>
		<pose>Unspecified</pose>
		<truncated>0</truncated>
		<difficult>0</difficult>
		<bndbox>
			<xmin>372</xmin>
			<ymin>202</ymin>
			<xmax>421</xmax>
			<ymax>281</ymax>
		</bndbox>
	</object>
	<object>
		<name>eggs</name>
		<pose>Unspecified</pose>
		<truncated>0</truncated>
		<difficult>0</difficult>
		<bndbox>
			<xmin>195</xmin>
			<ymin>418</ymin>
			<xmax>238</xmax>
			<ymax>507</ymax>
		</bndbox>
	</object>
</annotation>
